setup.py
PlayingWithDistributions/Binomialdistribution.py
PlayingWithDistributions/Gaussiandistribution.py
PlayingWithDistributions/Generaldistribution.py
PlayingWithDistributions/__init__.py
PlayingWithDistributions.egg-info/PKG-INFO
PlayingWithDistributions.egg-info/SOURCES.txt
PlayingWithDistributions.egg-info/dependency_links.txt
PlayingWithDistributions.egg-info/not-zip-safe
PlayingWithDistributions.egg-info/top_level.txt