Metadata-Version: 1.0
Name: PlayingWithDistributions
Version: 1.1
Summary: Gaussian and Binomial distributions
Home-page: UNKNOWN
Author: Oritseweyinmi Henry Ajagbawa
Author-email: weyinmiajagbawa@hotmail.com
License: UNKNOWN
Platform: UNKNOWN
